apicuron_client/__init__.py
apicuron_client/__main__.py
apicuron_client/api.py
apicuron_client/cli.py
apicuron_client/version.py
apicuron_client-0.1.3.dist-info/LICENSE
apicuron_client-0.1.3.dist-info/METADATA
apicuron_client-0.1.3.dist-info/WHEEL
apicuron_client-0.1.3.dist-info/entry_points.txt
apicuron_client-0.1.3.dist-info/top_level.txt
apicuron_client-0.1.3.dist-info/RECORD
